mcp_nlp/__init__.py
mcp_nlp/__main__.py
mcp_nlp/app.py
mcp_nlp/core/__init__.py
mcp_nlp/core/logging.py
mcp_nlp/core/middlewares.py
mcp_nlp/core/settings.py
mcp_nlp/resources/__init__.py
mcp_nlp/resources/version.py
mcp_nlp/services/__init__.py
mcp_nlp/services/text_distance.py
mcp_nlp/services/utils.py
mcp_nlp/tools/__init__.py
mcp_nlp/tools/text_distance.py
mcp_nlp-0.0.1.dist-info/METADATA
mcp_nlp-0.0.1.dist-info/WHEEL
mcp_nlp-0.0.1.dist-info/entry_points.txt
mcp_nlp-0.0.1.dist-info/licenses/LICENSE
mcp_nlp-0.0.1.dist-info/RECORD
