Metadata-Version: 2.4
Name: mcp-nlp
Version: 0.0.1
Summary: MCP-NLP is a Python package for Natural Language Processing tasks using the MCP
Author-email: tivaliy <vitaliy@kulanov.org.ua>
License-Expression: MIT
License-File: LICENSE
Requires-Python: >=3.12
Requires-Dist: click>=8.1.8
Requires-Dist: fastmcp==2.10.6
Requires-Dist: textdistance==4.6.2
